pyInterception_hotkeys/__init__.py
pyInterception_hotkeys/_hotkey.py
pyInterception_hotkeys/_keyStateTracker.py
pyInterception_hotkeys/_keyboard.py
pyinterception_hotkeys-0.1.8.dist-info/LICENSE
pyinterception_hotkeys-0.1.8.dist-info/METADATA
pyinterception_hotkeys-0.1.8.dist-info/WHEEL
pyinterception_hotkeys-0.1.8.dist-info/entry_points.txt
pyinterception_hotkeys-0.1.8.dist-info/top_level.txt
pyinterception_hotkeys-0.1.8.dist-info/RECORD
