Metadata-Version: 2.1
Name: pyinterception-hotkeys
Version: 0.1.8
Summary: A hotkeys and keyboard input library using PyInterception
Author-email: Yoonu <yoonu@yoonu.io>
License: MIT License
Classifier: Programming Language :: Python :: 3
Classifier: License :: OSI Approved :: MIT License
Classifier: Operating System :: OS Independent
Requires-Python: >=3.6
License-File: LICENSE
Requires-Dist: interception-python
Requires-Dist: pywin32
